eoreader/__init__.py
eoreader/__meta__.py
eoreader/env_vars.py
eoreader/exceptions.py
eoreader/keywords.py
eoreader/reader.py
eoreader/utils.py
eoreader/bands/__init__.py
eoreader/bands/band_names.py
eoreader/bands/bands.py
eoreader/bands/indices.py
eoreader/bands/mappings.py
eoreader/bands/sar_bands.py
eoreader/bands/spectral_bands.py
eoreader/data/cplx_no_calib_preprocess_default.xml
eoreader/data/cplx_s1_preprocess_default.xml
eoreader/data/cplx_s1_sm_preprocess_default.xml
eoreader/data/cplx_sar_preprocess_default.xml
eoreader/data/grd_no_calib_preprocess_default.xml
eoreader/data/grd_s1_preprocess_default.xml
eoreader/data/grd_sar_preprocess_default.xml
eoreader/data/grd_sar_preprocess_fallback.xml
eoreader/data/sar_despeckle_default.xml
eoreader/products/__init__.py
eoreader/products/custom_product.py
eoreader/products/product.py
eoreader/products/stac_product.py
eoreader/products/optical/__init__.py
eoreader/products/optical/dimap_v1_product.py
eoreader/products/optical/dimap_v2_product.py
eoreader/products/optical/gs2_product.py
eoreader/products/optical/hls_product.py
eoreader/products/optical/landsat_product.py
eoreader/products/optical/maxar_product.py
eoreader/products/optical/optical_product.py
eoreader/products/optical/pla_product.py
eoreader/products/optical/planet_product.py
eoreader/products/optical/pld_product.py
eoreader/products/optical/pneo_product.py
eoreader/products/optical/re_product.py
eoreader/products/optical/s2_e84_product.py
eoreader/products/optical/s2_mpc_product.py
eoreader/products/optical/s2_product.py
eoreader/products/optical/s2_theia_product.py
eoreader/products/optical/s3_olci_product.py
eoreader/products/optical/s3_product.py
eoreader/products/optical/s3_slstr_product.py
eoreader/products/optical/sky_product.py
eoreader/products/optical/spot45_product.py
eoreader/products/optical/spot67_product.py
eoreader/products/optical/sv1_product.py
eoreader/products/optical/vhr_product.py
eoreader/products/optical/vis1_product.py
eoreader-0.22.4.dist-info/licenses/LICENSE
eoreader-0.22.4.dist-info/licenses/NOTICE
eoreader-0.22.4.dist-info/METADATA
eoreader-0.22.4.dist-info/WHEEL
eoreader-0.22.4.dist-info/top_level.txt
eoreader-0.22.4.dist-info/RECORD
