Metadata-Version: 2.4
Name: eoreader
Version: 0.22.4
Summary: Remote-sensing opensource python library reading optical and SAR constellations, loading and stacking bands, clouds, DEM and spectral indices in a sensor-agnostic way.
Author-email: ICube-SERTIT <dev-sertit@unistra.fr>
License: Apache 2.0
Project-URL: Bug_Tracker, https://github.com/sertit/eoreader/issues
Project-URL: Documentation, https://eoreader.readthedocs.io/latest/
Project-URL: Source_Code, https://github.com/sertit/eoreader
Classifier: Development Status :: 5 - Production/Stable
Classifier: Intended Audience :: Developers
Classifier: Intended Audience :: Science/Research
Classifier: Natural Language :: English
Classifier: License :: OSI Approved :: Apache Software License
Classifier: Programming Language :: Python :: 3
Classifier: Programming Language :: Python :: 3.9
Classifier: Programming Language :: Python :: 3.10
Classifier: Programming Language :: Python :: 3.11
Classifier: Operating System :: OS Independent
Classifier: Topic :: Scientific/Engineering :: GIS
Classifier: Topic :: Software Development :: Libraries :: Python Modules
Requires-Python: >=3.9
License-File: LICENSE
License-File: NOTICE
Requires-Dist: lxml
Requires-Dist: h5netcdf
Requires-Dist: scipy
Requires-Dist: rasterio>=1.3.10
Requires-Dist: xarray>=2024.06.0
Requires-Dist: rioxarray>=0.10.0
Requires-Dist: odc-geo>=0.4.6
Requires-Dist: geopandas>=0.14.4
Requires-Dist: sertit[full]>=1.44.1
Requires-Dist: spyndex>=0.3.0
Requires-Dist: pyresample
Requires-Dist: zarr
Requires-Dist: rtree
Requires-Dist: cloudpathlib[s3]>=0.12.1
Requires-Dist: validators
Requires-Dist: methodtools
Requires-Dist: dicttoxml
Requires-Dist: tifffile
Requires-Dist: ephem
Provides-Extra: stac
Requires-Dist: pystac[validation]; extra == "stac"
Requires-Dist: stac-asset; extra == "stac"
Requires-Dist: planetary_computer; extra == "stac"
Dynamic: license-file
